jiggypedia/__init__.py
jiggypedia/jiggy_session.py
jiggypedia/query.py
Jiggypedia-0.0.5.dist-info/METADATA
Jiggypedia-0.0.5.dist-info/WHEEL
Jiggypedia-0.0.5.dist-info/top_level.txt
Jiggypedia-0.0.5.dist-info/RECORD
