Metadata-Version: 2.1
Name: Jiggypedia
Version: 0.0.5
Summary: Client library for Jiggypedia embedding search. For feeding your GPT a healthy diet of facts.
Author-email: Bill Kish <bk@jiggy.ai>, Amy Wang <why@jiggy.ai>
Project-URL: Homepage, https://github.com/jiggy-ai/jiggypedia
Project-URL: Bug Tracker, https://github.com/jiggy-ai/jiggypedia/issues
Classifier: Programming Language :: Python :: 3
Classifier: License :: OSI Approved :: Apache Software License
Classifier: Operating System :: OS Independent
Requires-Python: >=3.7
Requires-Dist: requests
Requires-Dist: pydantic
